<?xml version="1.0" encoding="utf-8" ?>

<Defs>
  <FleshTypeDef>
    <defName>RWBInsectoid</defName>
    <corpseCategory>CorpsesInsect</corpseCategory>
    <wounds>
      <li>
        <texture>Things/Pawn/Wounds/WoundA</texture>
        <color>0.23,0.20,0.17</color>
      </li>
      <li>
        <texture>Things/Pawn/Wounds/WoundB</texture>
        <color>0.23,0.20,0.17</color>
      </li>
      <li>
        <texture>Things/Pawn/Wounds/WoundC</texture>
        <color>0.23,0.20,0.17</color>
      </li>
    </wounds>
  </FleshTypeDef>
</Defs>